{
  "packageName": "Bambu Labs Printers",
  "author": "Ryan Elliott",
  "version": "0.1.4",
  "minimumHEVersion": "0.0",
  "dateReleased": "2023-04-27",
"releaseNotes": "v0.1.4 - Added printing status attribute.\nv0.1.3 - Minor tweaks.\nv0.1.2 - Added print time left and print percent completion. Added current print file. Added rounding for fan speed %.\nv0.1.1 - Add Actuator capability.\nv0.1.0 - Creation.\n\nFor further information or to report issues/request features, please see the community thread https://community.hubitat.com/t/release-iotawatt-beta/116875",
  "drivers": [
    {
      "id": "87c1b03a-086e-4e6c-9761-1dfb706eee01",
      "name": "BambuLabs",
      "namespace": "rle.bl",
      "location": "https://friedcheese2006.gateway.scarf.sh/BambuLabs_Driver.groovy",
      "required": true
    }
  ]
}